pytest_trio/__init__.py
pytest_trio/_version.py
pytest_trio/enable_trio_mode.py
pytest_trio/plugin.py
pytest_trio/_tests/__init__.py
pytest_trio/_tests/conftest.py
pytest_trio/_tests/helpers.py
pytest_trio/_tests/test_async_fixture.py
pytest_trio/_tests/test_async_yield_fixture.py
pytest_trio/_tests/test_basic.py
pytest_trio/_tests/test_clock_fixture.py
pytest_trio/_tests/test_contextvars.py
pytest_trio/_tests/test_fixture_mistakes.py
pytest_trio/_tests/test_fixture_names.py
pytest_trio/_tests/test_fixture_nursery.py
pytest_trio/_tests/test_fixture_ordering.py
pytest_trio/_tests/test_hypothesis_interaction.py
pytest_trio/_tests/test_sync_fixture.py
pytest_trio/_tests/test_trio_mode.py
pytest_trio-0.8.0.dist-info/LICENSE
pytest_trio-0.8.0.dist-info/LICENSE.APACHE2
pytest_trio-0.8.0.dist-info/LICENSE.MIT
pytest_trio-0.8.0.dist-info/METADATA
pytest_trio-0.8.0.dist-info/WHEEL
pytest_trio-0.8.0.dist-info/entry_points.txt
pytest_trio-0.8.0.dist-info/top_level.txt
pytest_trio-0.8.0.dist-info/RECORD
