Metadata-Version: 2.1
Name: pytest-trio
Version: 0.8.0
Summary: Pytest plugin for trio
Home-page: https://github.com/python-trio/pytest-trio
Author: Emmanuel Leblond
Author-email: emmanuel.leblond@gmail.com
License: MIT OR Apache-2.0
Keywords: async,pytest,testing,trio
Classifier: License :: OSI Approved :: MIT License
Classifier: License :: OSI Approved :: Apache Software License
Classifier: Operating System :: POSIX :: Linux
Classifier: Operating System :: MacOS :: MacOS X
Classifier: Operating System :: Microsoft :: Windows
Classifier: Programming Language :: Python :: 3 :: Only
Classifier: Programming Language :: Python :: 3.7
Classifier: Programming Language :: Python :: 3.8
Classifier: Programming Language :: Python :: 3.9
Classifier: Programming Language :: Python :: 3.10
Classifier: Programming Language :: Python :: 3.11
Classifier: Programming Language :: Python :: Implementation :: CPython
Classifier: Programming Language :: Python :: Implementation :: PyPy
Classifier: Topic :: System :: Networking
Classifier: Topic :: Software Development :: Testing
Classifier: Framework :: Hypothesis
Classifier: Framework :: Pytest
Classifier: Framework :: Trio
Requires-Python: >=3.7
License-File: LICENSE
License-File: LICENSE.APACHE2
License-File: LICENSE.MIT
